{
    "/js//main.min.js": "/js//main.min.js",
    "/js//login.min.js": "/js//login.min.js",
    "/js/bundle/dashboard.b7df3ba11157c34a.js": "/js/bundle/dashboard.b7df3ba11157c34a.js",
    "/js/bundle/products.b7df3ba11157c34a.js": "/js/bundle/products.b7df3ba11157c34a.js",
    "/js/bundle/index_products.b7df3ba11157c34a.js": "/js/bundle/index_products.b7df3ba11157c34a.js",
    "/js/bundle/store_product.b7df3ba11157c34a.js": "/js/bundle/store_product.b7df3ba11157c34a.js",
    "/js/bundle/edit_product.b7df3ba11157c34a.js": "/js/bundle/edit_product.b7df3ba11157c34a.js",
    "/js/bundle/detail_product.b7df3ba11157c34a.js": "/js/bundle/detail_product.b7df3ba11157c34a.js",
    "/js/bundle/barcode.b7df3ba11157c34a.js": "/js/bundle/barcode.b7df3ba11157c34a.js",
    "/js/bundle/count_stock.b7df3ba11157c34a.js": "/js/bundle/count_stock.b7df3ba11157c34a.js",
    "/js/bundle/Categories.b7df3ba11157c34a.js": "/js/bundle/Categories.b7df3ba11157c34a.js",
    "/js/bundle/Brands.b7df3ba11157c34a.js": "/js/bundle/Brands.b7df3ba11157c34a.js",
    "/js/bundle/units.b7df3ba11157c34a.js": "/js/bundle/units.b7df3ba11157c34a.js",
    "/js/bundle/adjustments.b7df3ba11157c34a.js": "/js/bundle/adjustments.b7df3ba11157c34a.js",
    "/js/bundle/index_adjustment.b7df3ba11157c34a.js": "/js/bundle/index_adjustment.b7df3ba11157c34a.js",
    "/js/bundle/store_adjustment.b7df3ba11157c34a.js": "/js/bundle/store_adjustment.b7df3ba11157c34a.js",
    "/js/bundle/edit_adjustment.b7df3ba11157c34a.js": "/js/bundle/edit_adjustment.b7df3ba11157c34a.js",
    "/js/bundle/transfers.b7df3ba11157c34a.js": "/js/bundle/transfers.b7df3ba11157c34a.js",
    "/js/bundle/index_transfer.b7df3ba11157c34a.js": "/js/bundle/index_transfer.b7df3ba11157c34a.js",
    "/js/bundle/store_transfer.b7df3ba11157c34a.js": "/js/bundle/store_transfer.b7df3ba11157c34a.js",
    "/js/bundle/edit_transfer.b7df3ba11157c34a.js": "/js/bundle/edit_transfer.b7df3ba11157c34a.js",
    "/js/bundle/accounts.b7df3ba11157c34a.js": "/js/bundle/accounts.b7df3ba11157c34a.js",
    "/js/bundle/transfer_money.b7df3ba11157c34a.js": "/js/bundle/transfer_money.b7df3ba11157c34a.js",
    "/js/bundle/expenses.b7df3ba11157c34a.js": "/js/bundle/expenses.b7df3ba11157c34a.js",
    "/js/bundle/index_expense.b7df3ba11157c34a.js": "/js/bundle/index_expense.b7df3ba11157c34a.js",
    "/js/bundle/store_expense.b7df3ba11157c34a.js": "/js/bundle/store_expense.b7df3ba11157c34a.js",
    "/js/bundle/edit_expense.b7df3ba11157c34a.js": "/js/bundle/edit_expense.b7df3ba11157c34a.js",
    "/js/bundle/expense_category.b7df3ba11157c34a.js": "/js/bundle/expense_category.b7df3ba11157c34a.js",
    "/js/bundle/deposits.b7df3ba11157c34a.js": "/js/bundle/deposits.b7df3ba11157c34a.js",
    "/js/bundle/index_deposit.b7df3ba11157c34a.js": "/js/bundle/index_deposit.b7df3ba11157c34a.js",
    "/js/bundle/store_deposit.b7df3ba11157c34a.js": "/js/bundle/store_deposit.b7df3ba11157c34a.js",
    "/js/bundle/edit_deposit.b7df3ba11157c34a.js": "/js/bundle/edit_deposit.b7df3ba11157c34a.js",
    "/js/bundle/deposit_category.b7df3ba11157c34a.js": "/js/bundle/deposit_category.b7df3ba11157c34a.js",
    "/js/bundle/quotations.b7df3ba11157c34a.js": "/js/bundle/quotations.b7df3ba11157c34a.js",
    "/js/bundle/store_quotation.b7df3ba11157c34a.js": "/js/bundle/store_quotation.b7df3ba11157c34a.js",
    "/js/bundle/edit_quotation.b7df3ba11157c34a.js": "/js/bundle/edit_quotation.b7df3ba11157c34a.js",
    "/js/bundle/detail_quotation.b7df3ba11157c34a.js": "/js/bundle/detail_quotation.b7df3ba11157c34a.js",
    "/js/bundle/change_to_sale.b7df3ba11157c34a.js": "/js/bundle/change_to_sale.b7df3ba11157c34a.js",
    "/js/bundle/purchases.b7df3ba11157c34a.js": "/js/bundle/purchases.b7df3ba11157c34a.js",
    "/js/bundle/index_purchases.b7df3ba11157c34a.js": "/js/bundle/index_purchases.b7df3ba11157c34a.js",
    "/js/bundle/store_purchase.b7df3ba11157c34a.js": "/js/bundle/store_purchase.b7df3ba11157c34a.js",
    "/js/bundle/edit_purchase.b7df3ba11157c34a.js": "/js/bundle/edit_purchase.b7df3ba11157c34a.js",
    "/js/bundle/create_purchase_return.b7df3ba11157c34a.js": "/js/bundle/create_purchase_return.b7df3ba11157c34a.js",
    "/js/bundle/detail_purchase.b7df3ba11157c34a.js": "/js/bundle/detail_purchase.b7df3ba11157c34a.js",
    "/js/bundle/sales.b7df3ba11157c34a.js": "/js/bundle/sales.b7df3ba11157c34a.js",
    "/js/bundle/index_sales.b7df3ba11157c34a.js": "/js/bundle/index_sales.b7df3ba11157c34a.js",
    "/js/bundle/store_sale.b7df3ba11157c34a.js": "/js/bundle/store_sale.b7df3ba11157c34a.js",
    "/js/bundle/edit_sale.b7df3ba11157c34a.js": "/js/bundle/edit_sale.b7df3ba11157c34a.js",
    "/js/bundle/create_sale_return.b7df3ba11157c34a.js": "/js/bundle/create_sale_return.b7df3ba11157c34a.js",
    "/js/bundle/detail_sale.b7df3ba11157c34a.js": "/js/bundle/detail_sale.b7df3ba11157c34a.js",
    "/js/bundle/shipment.b7df3ba11157c34a.js": "/js/bundle/shipment.b7df3ba11157c34a.js",
    "/js/bundle/sale_return.b7df3ba11157c34a.js": "/js/bundle/sale_return.b7df3ba11157c34a.js",
    "/js/bundle/index_sale_return.b7df3ba11157c34a.js": "/js/bundle/index_sale_return.b7df3ba11157c34a.js",
    "/js/bundle/edit_sale_return.b7df3ba11157c34a.js": "/js/bundle/edit_sale_return.b7df3ba11157c34a.js",
    "/js/bundle/detail_sale_return.b7df3ba11157c34a.js": "/js/bundle/detail_sale_return.b7df3ba11157c34a.js",
    "/js/bundle/purchase_return.b7df3ba11157c34a.js": "/js/bundle/purchase_return.b7df3ba11157c34a.js",
    "/js/bundle/index_purchase_return.b7df3ba11157c34a.js": "/js/bundle/index_purchase_return.b7df3ba11157c34a.js",
    "/js/bundle/edit_purchase_return.b7df3ba11157c34a.js": "/js/bundle/edit_purchase_return.b7df3ba11157c34a.js",
    "/js/bundle/detail_purchase_return.b7df3ba11157c34a.js": "/js/bundle/detail_purchase_return.b7df3ba11157c34a.js",
    "/js/bundle/hrm.b7df3ba11157c34a.js": "/js/bundle/hrm.b7df3ba11157c34a.js",
    "/js/bundle/employees.b7df3ba11157c34a.js": "/js/bundle/employees.b7df3ba11157c34a.js",
    "/js/bundle/index_employee.b7df3ba11157c34a.js": "/js/bundle/index_employee.b7df3ba11157c34a.js",
    "/js/bundle/store_employee.b7df3ba11157c34a.js": "/js/bundle/store_employee.b7df3ba11157c34a.js",
    "/js/bundle/edit_employee.b7df3ba11157c34a.js": "/js/bundle/edit_employee.b7df3ba11157c34a.js",
    "/js/bundle/detail_employee.b7df3ba11157c34a.js": "/js/bundle/detail_employee.b7df3ba11157c34a.js",
    "/js/bundle/company.b7df3ba11157c34a.js": "/js/bundle/company.b7df3ba11157c34a.js",
    "/js/bundle/departments.b7df3ba11157c34a.js": "/js/bundle/departments.b7df3ba11157c34a.js",
    "/js/bundle/designations.b7df3ba11157c34a.js": "/js/bundle/designations.b7df3ba11157c34a.js",
    "/js/bundle/office_shift.b7df3ba11157c34a.js": "/js/bundle/office_shift.b7df3ba11157c34a.js",
    "/js/bundle/attendance.b7df3ba11157c34a.js": "/js/bundle/attendance.b7df3ba11157c34a.js",
    "/js/bundle/holidays.b7df3ba11157c34a.js": "/js/bundle/holidays.b7df3ba11157c34a.js",
    "/js/bundle/payrolls.b7df3ba11157c34a.js": "/js/bundle/payrolls.b7df3ba11157c34a.js",
    "/js/bundle/leaves.b7df3ba11157c34a.js": "/js/bundle/leaves.b7df3ba11157c34a.js",
    "/js/bundle/leave_list.b7df3ba11157c34a.js": "/js/bundle/leave_list.b7df3ba11157c34a.js",
    "/js/bundle/leave_type.b7df3ba11157c34a.js": "/js/bundle/leave_type.b7df3ba11157c34a.js",
    "/js/bundle/People.b7df3ba11157c34a.js": "/js/bundle/People.b7df3ba11157c34a.js",
    "/js/bundle/Customers.b7df3ba11157c34a.js": "/js/bundle/Customers.b7df3ba11157c34a.js",
    "/js/bundle/Customers_without_ecommerce.b7df3ba11157c34a.js": "/js/bundle/Customers_without_ecommerce.b7df3ba11157c34a.js",
    "/js/bundle/Suppliers.b7df3ba11157c34a.js": "/js/bundle/Suppliers.b7df3ba11157c34a.js",
    "/js/bundle/Users.b7df3ba11157c34a.js": "/js/bundle/Users.b7df3ba11157c34a.js",
    "/js/bundle/settings.b7df3ba11157c34a.js": "/js/bundle/settings.b7df3ba11157c34a.js",
    "/js/bundle/permissions.b7df3ba11157c34a.js": "/js/bundle/permissions.b7df3ba11157c34a.js",
    "/js/bundle/groupPermission.b7df3ba11157c34a.js": "/js/bundle/groupPermission.b7df3ba11157c34a.js",
    "/js/bundle/store_permission.b7df3ba11157c34a.js": "/js/bundle/store_permission.b7df3ba11157c34a.js",
    "/js/bundle/edit_permission.b7df3ba11157c34a.js": "/js/bundle/edit_permission.b7df3ba11157c34a.js",
    "/js/bundle/sms_settings.b7df3ba11157c34a.js": "/js/bundle/sms_settings.b7df3ba11157c34a.js",
    "/js/bundle/sms_templates.b7df3ba11157c34a.js": "/js/bundle/sms_templates.b7df3ba11157c34a.js",
    "/js/bundle/email_templates.b7df3ba11157c34a.js": "/js/bundle/email_templates.b7df3ba11157c34a.js",
    "/js/bundle/pos_settings.b7df3ba11157c34a.js": "/js/bundle/pos_settings.b7df3ba11157c34a.js",
    "/js/bundle/payment_gateway.b7df3ba11157c34a.js": "/js/bundle/payment_gateway.b7df3ba11157c34a.js",
    "/js/bundle/mail_settings.b7df3ba11157c34a.js": "/js/bundle/mail_settings.b7df3ba11157c34a.js",
    "/js/bundle/module_settings.b7df3ba11157c34a.js": "/js/bundle/module_settings.b7df3ba11157c34a.js",
    "/js/bundle/update_settings.b7df3ba11157c34a.js": "/js/bundle/update_settings.b7df3ba11157c34a.js",
    "/js/bundle/Currencies.b7df3ba11157c34a.js": "/js/bundle/Currencies.b7df3ba11157c34a.js",
    "/js/bundle/Backup.b7df3ba11157c34a.js": "/js/bundle/Backup.b7df3ba11157c34a.js",
    "/js/bundle/Warehouses.b7df3ba11157c34a.js": "/js/bundle/Warehouses.b7df3ba11157c34a.js",
    "/js/bundle/System_settings.b7df3ba11157c34a.js": "/js/bundle/System_settings.b7df3ba11157c34a.js",
    "/js/bundle/payments_purchases.b7df3ba11157c34a.js": "/js/bundle/payments_purchases.b7df3ba11157c34a.js",
    "/js/bundle/payments_sales.b7df3ba11157c34a.js": "/js/bundle/payments_sales.b7df3ba11157c34a.js",
    "/js/bundle/payments_purchases_returns.b7df3ba11157c34a.js": "/js/bundle/payments_purchases_returns.b7df3ba11157c34a.js",
    "/js/bundle/payments_sales_returns.b7df3ba11157c34a.js": "/js/bundle/payments_sales_returns.b7df3ba11157c34a.js",
    "/js/bundle/profit_and_loss.b7df3ba11157c34a.js": "/js/bundle/profit_and_loss.b7df3ba11157c34a.js",
    "/js/bundle/inventory_valuation_summary.b7df3ba11157c34a.js": "/js/bundle/inventory_valuation_summary.b7df3ba11157c34a.js",
    "/js/bundle/expenses_report.b7df3ba11157c34a.js": "/js/bundle/expenses_report.b7df3ba11157c34a.js",
    "/js/bundle/deposits_report.b7df3ba11157c34a.js": "/js/bundle/deposits_report.b7df3ba11157c34a.js",
    "/js/bundle/quantity_alerts.b7df3ba11157c34a.js": "/js/bundle/quantity_alerts.b7df3ba11157c34a.js",
    "/js/bundle/warehouse_report.b7df3ba11157c34a.js": "/js/bundle/warehouse_report.b7df3ba11157c34a.js",
    "/js/bundle/sales_report.b7df3ba11157c34a.js": "/js/bundle/sales_report.b7df3ba11157c34a.js",
    "/js/bundle/product_sales_report.b7df3ba11157c34a.js": "/js/bundle/product_sales_report.b7df3ba11157c34a.js",
    "/js/bundle/purchase_report.b7df3ba11157c34a.js": "/js/bundle/purchase_report.b7df3ba11157c34a.js",
    "/js/bundle/product_purchases_report.b7df3ba11157c34a.js": "/js/bundle/product_purchases_report.b7df3ba11157c34a.js",
    "/js/bundle/customers_report.b7df3ba11157c34a.js": "/js/bundle/customers_report.b7df3ba11157c34a.js",
    "/js/bundle/detail_customer_report.b7df3ba11157c34a.js": "/js/bundle/detail_customer_report.b7df3ba11157c34a.js",
    "/js/bundle/providers_report.b7df3ba11157c34a.js": "/js/bundle/providers_report.b7df3ba11157c34a.js",
    "/js/bundle/detail_supplier_report.b7df3ba11157c34a.js": "/js/bundle/detail_supplier_report.b7df3ba11157c34a.js",
    "/js/bundle/top_selling_products.b7df3ba11157c34a.js": "/js/bundle/top_selling_products.b7df3ba11157c34a.js",
    "/js/bundle/product_report.b7df3ba11157c34a.js": "/js/bundle/product_report.b7df3ba11157c34a.js",
    "/js/bundle/detail_product_report.b7df3ba11157c34a.js": "/js/bundle/detail_product_report.b7df3ba11157c34a.js",
    "/js/bundle/top_customers.b7df3ba11157c34a.js": "/js/bundle/top_customers.b7df3ba11157c34a.js",
    "/js/bundle/stock_report.b7df3ba11157c34a.js": "/js/bundle/stock_report.b7df3ba11157c34a.js",
    "/js/bundle/detail_stock_report.b7df3ba11157c34a.js": "/js/bundle/detail_stock_report.b7df3ba11157c34a.js",
    "/js/bundle/users_report.b7df3ba11157c34a.js": "/js/bundle/users_report.b7df3ba11157c34a.js",
    "/js/bundle/detail_user_report.b7df3ba11157c34a.js": "/js/bundle/detail_user_report.b7df3ba11157c34a.js",
    "/js/bundle/profile.b7df3ba11157c34a.js": "/js/bundle/profile.b7df3ba11157c34a.js",
    "/js/bundle/pos.b7df3ba11157c34a.js": "/js/bundle/pos.b7df3ba11157c34a.js",
    "/js/bundle/pos_draft.b7df3ba11157c34a.js": "/js/bundle/pos_draft.b7df3ba11157c34a.js",
    "/js/bundle/NotFound.b7df3ba11157c34a.js": "/js/bundle/NotFound.b7df3ba11157c34a.js",
    "/js/bundle/not_authorize.b7df3ba11157c34a.js": "/js/bundle/not_authorize.b7df3ba11157c34a.js",
    "/js/bundle/largeSidebar.b7df3ba11157c34a.js": "/js/bundle/largeSidebar.b7df3ba11157c34a.js",
    "/js/bundle/customizer.b7df3ba11157c34a.js": "/js/bundle/customizer.b7df3ba11157c34a.js",
    "/js/bundle/vue-perfect-scrollbar.b7df3ba11157c34a.js": "/js/bundle/vue-perfect-scrollbar.b7df3ba11157c34a.js"
}
